{
  "@context": "http://schema.org",
  "@type": "Person",
  "name": "Robin Millette",
  "image": "/profile.jpg",
  "email": "robin@millette.info",
  "identifier": "dat://26620b74b6878c872ff243a151974aad5d52349bda12a02c19098421fce8bef4/",
  "url": "https://profile-millette.hashbase.io/",
  "sameAs": [
    "https://profile-millette.other.example.com/",
    "https://profile-millette.another.example.com/"
  ],
  "description": "Robin Millette's dat profile.",
  "follows": [
    {"url": "dat://.../", "name": "Bob"},
    {"url": "dat://.../", "name": "Carla"},
    {"url": "dat://.../", "name": "Dan"}
  ]
}
